Metadata-Version: 1.1
Name: cloud-init-seed
Version: 0.3.0
Summary: Create cloud-init compatible image seeds
Home-page: https://github.com/toabctl/cloud-init-seed
Author: Thomas Bechtold
Author-email: thomasbechtold@jpberlin.de
License: UNKNOWN
Platform: UNKNOWN
Classifier: Development Status :: 4 - Beta
Classifier: Environment :: Console
Classifier: Intended Audience :: End Users/Desktop
Classifier: Intended Audience :: Developers
Classifier: Intended Audience :: System Administrators
Classifier: License :: OSI Approved :: Apache Software License
Classifier: Programming Language :: Python
Classifier: Topic :: Utilities
